requests_aws_sign/__init__.py
requests_aws_sign/requests_aws_sign.py
requests_aws_sign-0.1.5.dist-info/METADATA
requests_aws_sign-0.1.5.dist-info/RECORD
requests_aws_sign-0.1.5.dist-info/WHEEL
requests_aws_sign-0.1.5.dist-info/top_level.txt
