Metadata-Version: 2.1
Name: requests-aws-sign
Version: 0.1.5
Summary: This package provides AWS V4 request signing using the requests library.
Home-page: https://github.com/jmenga/requests-aws-sign
Author: Justin Menga
Author-email: justin.menga@gmail.com
License: ISC
Keywords: requests aws
Platform: UNKNOWN
Classifier: Development Status :: 4 - Beta
Classifier: Intended Audience :: Developers
Classifier: Programming Language :: Python
Classifier: Programming Language :: Python :: 2
Classifier: Programming Language :: Python :: 2.6
Classifier: Programming Language :: Python :: 2.7
Classifier: Programming Language :: Python :: 3
Classifier: Programming Language :: Python :: 3.3
Classifier: Programming Language :: Python :: 3.4
Classifier: Programming Language :: Python :: 3.5
Classifier: License :: OSI Approved :: ISC License (ISCL)
Provides: requests_aws_sign
Requires-Dist: requests (>=2.0.0)
Requires-Dist: boto3
